blog/__init__.py
blog/api/__init__.py
blog/api/apps.py
blog/api/urls.py
blog/apps/__init__.py
blog/apps/articles/__init__.py
blog/apps/articles/apps.py
blog/apps/articles/migrations/0001_initial.py
blog/apps/articles/migrations/0002_initial.py
blog/apps/articles/migrations/0003_alter_blogarticle_content.py
blog/apps/articles/migrations/0004_alter_blogarticle_content.py
blog/apps/articles/migrations/0005_alter_blogarticle_content.py
blog/apps/articles/migrations/0006_alter_blogarticle_content.py
blog/apps/articles/migrations/0007_alter_blogarticle_content.py
blog/apps/articles/migrations/0008_alter_blogarticle_content.py
blog/apps/articles/migrations/__init__.py
blog/apps/articles/models.py
blog/apps/articles/tests/__init__.py
blog/apps/articles/tests/test_models.py
blog/apps/categories/__init__.py
blog/apps/categories/apps.py
blog/apps/categories/migrations/0001_initial.py
blog/apps/categories/migrations/__init__.py
blog/apps/categories/models.py
blog/apps/categories/tests/__init__.py
blog/apps/categories/tests/test_models.py
blog/apps/home/__init__.py
blog/apps/home/apps.py
blog/apps/home/migrations/0001_initial.py
blog/apps/home/migrations/0002_create_homepage.py
blog/apps/home/migrations/__init__.py
blog/apps/home/models.py
blog/apps/home/tests/__init__.py
blog/apps/home/tests/test_models.py
blog/apps/indexes/__init__.py
blog/apps/indexes/apps.py
blog/apps/indexes/migrations/0001_initial.py
blog/apps/indexes/migrations/0002_alter_blogindex_content.py
blog/apps/indexes/migrations/0003_alter_blogindex_content.py
blog/apps/indexes/migrations/0004_alter_blogindex_content.py
blog/apps/indexes/migrations/0005_alter_blogindex_content.py
blog/apps/indexes/migrations/__init__.py
blog/apps/indexes/models.py
blog/apps/indexes/tests/__init__.py
blog/apps/indexes/tests/test_models.py
blog/apps/mixins.py
blog/apps/signals.py
blog/apps/tags/__init__.py
blog/apps/tags/apps.py
blog/apps/tags/migrations/0001_initial.py
blog/apps/tags/migrations/__init__.py
django_w_blog-0.2.5.dist-info/METADATA
django_w_blog-0.2.5.dist-info/WHEEL
django_w_blog-0.2.5.dist-info/licenses/LICENSE
django_w_blog-0.2.5.dist-info/RECORD
